{"stats":{"minecraft:used":{"minecraft:diamond_pickaxe":23,"minecraft:stone":24,"minecraft:deepslate":41},"minecraft:picked_up":{"minecraft:deepslate":1,"minecraft:cobbled_deepslate":2,"minecraft:cobblestone":6},"minecraft:dropped":{"minecraft:diamond_pickaxe":1},"minecraft:custom":{"minecraft:jump":1,"minecraft:time_since_rest":9703,"minecraft:leave_game":1,"minecraft:play_time":9703,"minecraft:time_since_death":9703,"minecraft:walk_one_cm":14676,"minecraft:total_world_time":9712,"minecraft:drop":1},"minecraft:mined":{"minecraft:stone":14,"minecraft:deepslate":9}},"DataVersion":3105}